{
  "$schema": "https://raw.githubusercontent.com/streetsidesoftware/cspell/main/cspell.schema.json",
  "version": "0.2",
  "language": "en",
  "useGitignore": true,
  "dictionaries": [
    "bash",
    "powershell",
    "python",
    "softwareTerms",
    "companies",
  ],
  "ignorePaths": [
    "*.lock",
    "*.json",
    "compose.yaml",
    "config/**/scripts/**",
    "config/**/module.py",
    "machines/**/scripts/**",
    "machines/**/openclaw/**",
    "machines/**/manifest.py",
  ],
  "words": [
    // names
    "fmohammedrmt",
    "mfareedrmt",
    "fareed",
    "mohdfareed",
    "mohds",
    "fareed",
    "macbook",
    "homelab",
    // tools
    "winget",
    "tailnet",
    "ghcs",
    "openclaw",
    "cowork",
    "chatmock",
    "linuxbrew",
    "shellenv",
    "worktree",
    // terms
    "Eeuo",
    "bootstrapper",
    "autogroup",
    "keygen",
    "testpaths",
    "hardlink",
    "tskey",
    "wslinfo",
    "pkill",
    "nohup",
    "startfile",
    "winerror",
    "keepalive",
    "spath",
    "USERSPACE",
  ],
}
